certbot_dns_jeffdev/__init__.py
certbot_dns_jeffdev/py.typed
certbot_dns_jeffdev/_internal/__init__.py
certbot_dns_jeffdev/_internal/dns_jeffdev.py
certbot_dns_jeffdev-3.0.0.dist-info/licenses/LICENSE
certbot_dns_jeffdev-3.0.0.dist-info/METADATA
certbot_dns_jeffdev-3.0.0.dist-info/WHEEL
certbot_dns_jeffdev-3.0.0.dist-info/entry_points.txt
certbot_dns_jeffdev-3.0.0.dist-info/top_level.txt
certbot_dns_jeffdev-3.0.0.dist-info/RECORD
